Metadata-Version: 1.0
Name: ilaev-module
Version: 0.1.0
Summary: A example Python package
Home-page: UNKNOWN
Author: Nikita Ilaev
Author-email: UNKNOWN
License: UNKNOWN
Platform: UNKNOWN
